msal_streamlit_authentication/__init__.py
msal_streamlit_authentication/frontend/dist/assets/index-487dc779.js
msal_streamlit_authentication/frontend/dist/assets/index-5dff78b6.css
msal_streamlit_authentication/frontend/dist/index.html
msal_streamlit_authentication_dentro-1.0.9.dist-info/LICENSE
msal_streamlit_authentication_dentro-1.0.9.dist-info/METADATA
msal_streamlit_authentication_dentro-1.0.9.dist-info/WHEEL
msal_streamlit_authentication_dentro-1.0.9.dist-info/RECORD
