Metadata-Version: 2.1
Name: msal_streamlit_authentication_dentro
Version: 1.0.9
Summary: Streamlit Authentication library based on MSAL.JS
Home-page: https://github.com/dentro-innovation/msal_streamlit_authentication
Author: Michael Staal-Olsen
Requires-Python: >=3.7
Classifier: Programming Language :: Python :: 3
Classifier: Programming Language :: Python :: 3.7
Classifier: Programming Language :: Python :: 3.8
Classifier: Programming Language :: Python :: 3.9
Classifier: Programming Language :: Python :: 3.10
Classifier: Programming Language :: Python :: 3.11
Classifier: Programming Language :: Python :: 3.12
Requires-Dist: streamlit
Project-URL: Repository, https://github.com/dentro-innovation/msal_streamlit_authentication
